storytelling/__init__.py
storytelling/__main__.py
storytelling/ceremonial_diary.py
storytelling/cli.py
storytelling/coaia_fuse.py
storytelling/config.py
storytelling/core.py
storytelling/data_models.py
storytelling/enhanced_rag.py
storytelling/graph.py
storytelling/iaip_bridge.py
storytelling/llm_providers.py
storytelling/logger.py
storytelling/openrouter_patch.py
storytelling/prompts.py
storytelling/rag.py
storytelling/session_manager.py
storytelling/web_fetcher.py
storytelling-0.2.21.dist-info/licenses/LICENSE
storytelling_mcp/storytelling_mcp/__init__.py
storytelling_mcp/storytelling_mcp/server.py
storytelling_mcp/storytelling_mcp/setup.py
storytelling-0.2.21.dist-info/METADATA
storytelling-0.2.21.dist-info/WHEEL
storytelling-0.2.21.dist-info/entry_points.txt
storytelling-0.2.21.dist-info/top_level.txt
storytelling-0.2.21.dist-info/RECORD
